{
  "root": {
    "cellular organisms": {
      "Eukaryota": {
        "Opisthokonta": {
          "Opisthokonta incertae sedis": {
            "Corallochytrium": {
              "Corallochytrium limacisporum": {},
              "environmental samples": {
                "uncultured Corallochytrium": {}
              },
              "unclassified Corallochytrium": {
                "Corallochytrium sp. LM574": {},
                "Corallochytrium sp. LM578": {}
              }
            },
            "Syssomonas": {
              "Syssomonas multiformis": {},
              "unclassified Syssomonas": {
                "Syssomonas sp.": {}
              }
            },
            "Tunicaraptor": {
              "Tunicaraptor unikontum": {}
            }
          },
          "Ichthyosporea": {
            "Dermocystida": {
              "Dermocystidium": {
                "Dermocystidium salmonis": {},
                "Dermocystidium percae": {},
                "unclassified Dermocystidium": {
                  "Dermocystidium sp.": {},
                  "Dermocystidium sp. CM-2002": {},
                  "Dermocystidium sp. BZhang-2021a": {}
                },
                "Dermocystidium anguillae": {},
                "Dermocystidium koi": {}
              },
              "Rhinosporidium": {
                "Rhinosporidium seeberi": {},
                "Rhinosporidium cygnus": {},
                "unclassified Rhinosporidium": {
                  "Rhinosporidium sp. ex Canis familiaris": {},
                  "Rhinosporidium sp.": {}
                }
              },
              "Sphaerothecum": {
                "Sphaerothecum destruens": {},
                "Sphaerothecum caipira": {}
              },
              "Amphibiocystidium": {
                "Amphibiocystidium ranae": {},
                "unclassified Amphibiocystidium": {
                  "Amphibiocystidium sp. viridescens": {},
                  "Amphibiocystidium sp. CI07": {},
                  "Amphibiocystidium sp.": {}
                }
              },
              "Dermosporidium": {
                "Dermosporidium hylarum": {}
              },
              "Amphibiothecum": {
                "Amphibiothecum penneri": {}
              },
              "unclassified Dermocystida": {
                "Dermocystida sp. Larzac/A-f": {},
                "Dermocystida sp. Larzac/B-m": {},
                "Dermocystida sp. Larzac/C-f": {},
                "Dermocystida sp.": {}
              },
              "environmental samples": {
                "uncultured Dermocystida": {},
                "uncultured Rhinosporideacae": {}
              },
              "Valentines": {
                "Valentines rwandae": {}
              }
            },
            "Ichthyophonida": {
              "Psorospermium": {
                "Psorospermium haeckeli": {},
                "unclassified Psorospermium": {
                  "Psorospermium sp.": {}
                }
              },
              "Sphaeroforma": {
                "Sphaeroforma arctica": {
                  "Sphaeroforma arctica JP610": {}
                },
                "Sphaeroforma gastrica": {},
                "Sphaeroforma nootkatensis": {},
                "Sphaeroforma tapetis": {},
                "Sphaeroforma napiecek": {},
                "Sphaeroforma sirkka": {},
                "Sphaeroforma sp.": {}
              },
              "Anurofeca": {
                "Anurofeca richardsi": {},
                "unclassified Anurofeca": {
                  "Anurofeca sp. LAH-2003": {},
                  "Anurofeca sp.": {}
                }
              },
              "Pseudoperkinsus": {
                "unclassified Pseudoperkinsus": {
                  "Pseudoperkinsus sp.": {}
                }
              },
              "Palavasciaceae": {
                "Palavascia": {
                  "Palavascia patagonica": {},
                  "Palavascia sphaeromae": {}
                }
              },
              "Eccrinaceae": {
                "Enterobryus": {
                  "Enterobryus halophilus": {},
                  "Enterobryus oxidi": {},
                  "unclassified Enterobryus": {
                    "Enterobryus sp. CMJ-2003": {},
                    "Enterobryus cf. euryuri ONT-3-W6": {},
                    "Enterobryus sp. CO-16-W6": {},
                    "Enterobryus sp. CR-LS-C1": {},
                    "Enterobryus sp. FL-2-W7": {},
                    "Enterobryus sp. ID-163-G5": {},
                    "Enterobryus sp. ID-165-G2": {},
                    "Enterobryus sp. ID-165-G4": {},
                    "Enterobryus sp. KY-5-P5": {},
                    "Enterobryus sp. MA-11-C1": {},
                    "Enterobryus sp. Mex-4-C1": {},
                    "Enterobryus sp. SPA-10-C6": {},
                    "Enterobryus sp. SPA-2-C10": {},
                    "Enterobryus sp.": {}
                  }
                },
                "Enteromyces": {
                  "Enteromyces callianassae": {}
                },
                "Taeniellopsis": {
                  "unclassified Taeniellopsis": {
                    "Taeniellopsis sp. CMJ-2003": {}
                  }
                },
                "Eccrinidus": {
                  "Eccrinidus flexilis": {},
                  "unclassified Eccrinidus": {
                    "Eccrinidus sp.": {}
                  }
                },
                "Alacrinella": {
                  "Alacrinella limnoriae": {}
                },
                "Astreptonema": {
                  "Astreptonema gammari": {},
                  "unclassified Astreptonema": {
                    "Astreptonema sp. CMJ-2003": {},
                    "Astreptonema sp. WA-3-C3": {}
                  }
                },
                "Taeniella": {
                  "Taeniella carcini": {}
                },
                "Enteropogon": {
                  "Enteropogon sexuale": {}
                },
                "Arundinula": {
                  "Arundinula opeongoensis": {},
                  "unclassified Arundinula": {
                    "Arundinula sp. LA-9-W1g": {},
                    "Arundinula sp. LA-9-W2a": {}
                  }
                },
                "Leidyomyces": {
                  "Leidyomyces attenuatus": {},
                  "unclassified Leidyomyces": {
                    "Leidyomyces sp. GUA-X-13": {},
                    "Leidyomyces sp. GUA-X-18": {},
                    "Leidyomyces sp. Mex-38-C8": {}
                  }
                }
              },
              "Amoebidiaceae": {
                "Amoebidium": {
                  "Amoebidium parasiticum": {
                    "Amoebidium parasiticum JAP-7-2": {}
                  },
                  "Amoebidium appalachense": {},
                  "unclassified Amoebidium": {
                    "Amoebidium sp. TN-27-W4": {},
                    "Amoebidium sp.": {}
                  }
                },
                "Paramoebidium": {
                  "unclassified Paramoebidium": {
                    "Paramoebidium sp. CMJ-2003": {},
                    "Paramoebidium sp. ALG-9-W10": {},
                    "Paramoebidium sp. AR-30-C7": {},
                    "Paramoebidium sp. AR-30-C9": {},
                    "Paramoebidium sp. AR-31-C31": {},
                    "Paramoebidium sp. AR-31-C7": {},
                    "Paramoebidium sp. BC-5a-W6": {},
                    "Paramoebidium sp. CAL-17-L1": {},
                    "Paramoebidium sp. CAL-17-L6": {},
                    "Paramoebidium sp. CO-16-W12": {},
                    "Paramoebidium sp. CO-3-W13": {},
                    "Paramoebidium sp. DR-16-C8": {},
                    "Paramoebidium sp. ID-156-T1": {},
                    "Paramoebidium sp. ID-65e-E1": {},
                    "Paramoebidium sp. KS-61-W20": {},
                    "Paramoebidium sp. MA-3-W51": {},
                    "Paramoebidium sp. ME-2-W3": {},
                    "Paramoebidium sp. MO-19-W15": {},
                    "Paramoebidium sp. Mex-17-W2": {},
                    "Paramoebidium sp. NF-10-W15": {},
                    "Paramoebidium sp. NOR-10-W1": {},
                    "Paramoebidium sp. NOR-10-W10a": {},
                    "Paramoebidium sp. NOR-10-W15": {},
                    "Paramoebidium sp. NOR-16-W3": {},
                    "Paramoebidium sp. NOR-21-W5": {},
                    "Paramoebidium sp. NOR-3-1": {},
                    "Paramoebidium sp. NOR-3-W2": {},
                    "Paramoebidium sp. NOR-35-3": {},
                    "Paramoebidium sp. NOR-4-W9": {},
                    "Paramoebidium sp. NOR-40-W2": {},
                    "Paramoebidium sp. NOR-40-W8": {},
                    "Paramoebidium sp. NOR-5-2": {},
                    "Paramoebidium sp. NOR-5-W14": {},
                    "Paramoebidium sp. NOR-50-W2": {},
                    "Paramoebidium sp. NOR-54-2": {},
                    "Paramoebidium sp. NOR-54-W10": {},
                    "Paramoebidium sp. NOR-54-W17": {},
                    "Paramoebidium sp. NOR-61-W11": {},
                    "Paramoebidium sp. NOR-7-W2": {},
                    "Paramoebidium sp. NS-16-W2": {},
                    "Paramoebidium sp. NS-24-W16": {},
                    "Paramoebidium sp. NS-34-W17": {},
                    "Paramoebidium sp. NS-35-L2": {},
                    "Paramoebidium sp. NS-35-W14": {},
                    "Paramoebidium sp. NS-35-W18": {},
                    "Paramoebidium sp. NS-35-W22b": {},
                    "Paramoebidium sp. NS-35-W8": {},
                    "Paramoebidium sp. NS-6-W8-10": {},
                    "Paramoebidium sp. NS-X-17": {},
                    "Paramoebidium sp. NS-X-29": {},
                    "Paramoebidium sp. NY-3-C7": {},
                    "Paramoebidium sp. ONT-X-10": {},
                    "Paramoebidium sp. OR-13-W1": {},
                    "Paramoebidium sp. OR-14-W1": {},
                    "Paramoebidium sp. OR-3-W12": {},
                    "Paramoebidium sp. PA-2-W2": {},
                    "Paramoebidium sp. PEI-X-12": {},
                    "Paramoebidium sp. RMBL-71-3": {},
                    "Paramoebidium sp. RMBL-72-3": {},
                    "Paramoebidium sp. RMBL-75-1": {},
                    "Paramoebidium sp. TN-13-W20": {},
                    "Paramoebidium sp. TN-38-W13": {},
                    "Paramoebidium sp. TN-38-W15": {},
                    "Paramoebidium sp. UT-1-W14": {},
                    "Paramoebidium sp. UT-2-W5": {},
                    "Paramoebidium sp. VT-3-W1": {}
                  },
                  "Paramoebidium stipula": {},
                  "Paramoebidium cf. grande ID-164-G2": {},
                  "Paramoebidium avitruviense": {},
                  "Paramoebidium ecdyonuridae": {},
                  "Paramoebidium corpulentum": {},
                  "Paramoebidium curvum": {},
                  "Paramoebidium hamatum": {}
                }
              },
              "unclassified Ichthyophonida": {
                "Ichthyophonida sp.": {}
              },
              "environmental samples": {
                "uncultured Eccrinales": {}
              },
              "Creolimax": {
                "Creolimax fragrantissima": {},
                "unclassified Creolimax": {
                  "Creolimax sp.": {}
                }
              },
              "Abeoforma": {
                "Abeoforma whisleri": {}
              },
              "Parataeniellaceae": {
                "Parataeniella": {
                  "Parataeniella armadillidii": {},
                  "Parataeniella dilatata": {},
                  "unclassified Parataeniella": {
                    "Parataeniella sp. Boi-14-W5": {},
                    "Parataeniella sp. NOR-1-W1": {}
                  }
                }
              },
              "Ichthyophonidae": {
                "Ichthyophonus": {
                  "Ichthyophonus hoferi": {},
                  "Ichthyophonus irregularis": {},
                  "unclassified Ichthyophonus": {
                    "Ichthyophonus sp. D5": {},
                    "Ichthyophonus sp. A3": {},
                    "Ichthyophonus sp. ex Theragra chalcogramma": {},
                    "Ichthyophonus sp. JLG-2013a": {},
                    "Ichthyophonus sp. JLG-2013b": {},
                    "Ichthyophonus sp. JLG-2013c": {},
                    "Ichthyophonus sp. JLG-2013d": {},
                    "Ichthyophonus sp. JLG-2013e": {},
                    "Ichthyophonus sp. JLG-2013f": {},
                    "Ichthyophonus sp. ID-155-N1-2": {},
                    "Ichthyophonus sp. ID-155-N2-1": {},
                    "Ichthyophonus sp.": {}
                  }
                },
                "unclassified Ichthyophonidae": {
                  "Ichthyophonidae sp.": {}
                }
              },
              "Ichthyophonida incertae sedis": {
                "Caullerya": {
                  "Caullerya mesnili": {}
                }
              }
            },
            "environmental samples": {
              "uncultured mesomycete ikaite un-c53": {},
              "Ichthyophonida gen. sp. LKM51": {},
              "uncultured Amoebidium": {},
              "uncultured Ichthyosporea": {}
            },
            "unclassified Ichthyosporea": {
              "Ichthyosporea sp. ex Tenebrio molitor": {},
              "Ichthyosporea sp. NK52": {},
              "Ichthyosporea sp. XGB-2017a": {},
              "Ichthyosporea sp.": {}
            },
            "Pirum": {
              "Pirum gemmata": {}
            }
          },
          "environmental samples": {
            "uncultured opisthokont": {}
          },
          "unclassified Opisthokonta": {
            "Opisthokonta sp. LC-2017": {},
            "Holomycota sp.": {},
            "Holomycota sp. clade GS01": {},
            "Cristidiscoidea sp.": {},
            "Opisthokonta sp.": {}
          },
          "Aphelida": {
            "Aphelidea": {
              "Amoeboaphelidium": {
                "Amoeboaphelidium protococcarum": {},
                "Amoeboaphelidium occidentale": {},
                "unclassified Amoeboaphelidium": {
                  "Amoeboaphelidium sp. WZ01": {}
                }
              },
              "environmental samples": {
                "uncultured Aphelidea": {},
                "uncultured Amoeboaphelidium": {}
              },
              "Aphelidiaceae": {
                "Aphelidium": {
                  "Aphelidium aff. melosirae P-1": {},
                  "Aphelidium tribonematis": {},
                  "Aphelidium desmodesmi": {},
                  "Aphelidium collabens": {},
                  "Aphelidium arduennense": {},
                  "Aphelidium insulamus": {},
                  "Aphelidium parallelum": {}
                },
                "Paraphelidium": {
                  "Paraphelidium letcheri": {},
                  "Paraphelidium tribonematis": {},
                  "unclassified Paraphelidium": {
                    "Paraphelidium sp.": {}
                  }
                },
                "unclassified Aphelidiaceae": {
                  "Aphelidea sp.": {},
                  "Aphelidium sp.": {},
                  "Aphelidiaceae sp.": {}
                },
                "environmental samples": {
                  "uncultured Aphelidiaceae": {}
                },
                "Protaphelidium": {
                  "Protaphelidium rhizoclonii": {}
                }
              }
            },
            "unclassified Aphelida": {
              "Aphelida sp.": {}
            }
          },
          "Rotosphaerida": {
            "Nucleariidae": {
              "Nuclearia": {
                "Nuclearia delicatula": {},
                "Nuclearia moebiusi": {},
                "Nuclearia simplex": {},
                "Nuclearia pattersoni": {},
                "Nuclearia thermophila": {},
                "unclassified Nuclearia": {
                  "Nuclearia sp. W3": {},
                  "Nuclearia sp. 2H": {},
                  "Nuclearia sp. D5": {},
                  "Nuclearia sp. N SD-2013": {},
                  "Nuclearia sp. A": {},
                  "Nuclearia sp. A5": {},
                  "Nuclearia sp. K": {},
                  "Nuclearia sp. D6": {},
                  "Nuclearia sp. A2": {},
                  "Nuclearia sp. B4": {},
                  "Nuclearia sp. NZ": {},
                  "Nuclearia sp. A1": {},
                  "Nuclearia sp. D1": {},
                  "Nuclearia sp. B6": {},
                  "Nuclearia sp. D4": {},
                  "Nuclearia sp. S4": {},
                  "Nuclearia sp. D": {},
                  "Nuclearia sp. G": {},
                  "Nuclearia sp. B3": {},
                  "Nuclearia sp. B1": {},
                  "Nuclearia sp.": {},
                  "Nuclearia sp. 1 SD-2018": {}
                },
                "Nuclearia leuckarti": {}
              },
              "environmental samples": {
                "uncultured Nucleariidae": {},
                "uncultured Nuclearia": {}
              },
              "unclassified Nucleariidae": {
                "Nucleariidae sp.": {}
              }
            },
            "Parvularia": {
              "Parvularia atlantis": {},
              "unclassified Parvularia": {
                "Parvularia sp.": {}
              }
            },
            "Fonticulaceae": {
              "Fonticula": {
                "Fonticula alba": {}
              }
            },
            "unclassified Fonticulida": {
              "Fonticula-like sp. SCN 57-25": {},
              "Fonticulida sp.": {}
            },
            "Rotosphaerida incertae sedis": {
              "Pompholyxophrys": {
                "Pompholyxophrys punicea": {},
                "unclassified Pompholyxophrys": {
                  "Pompholyxophrys sp.": {}
                }
              },
              "Lithocolla": {
                "Lithocolla globosa": {},
                "unclassified Lithocolla": {
                  "Lithocolla sp.": {}
                }
              }
            },
            "unclassified Rotosphaerida": {
              "Rotosphaerida sp.": {}
            }
          },
          "Filasterea": {
            "Ministeria": {
              "Ministeria vibrans": {
                "Ministeria vibrans ATCC 50519": {}
              }
            },
            "Capsaspora": {
              "Capsaspora owczarzaki": {
                "Capsaspora owczarzaki ATCC 30864": {}
              },
              "unclassified Capsaspora": {
                "Capsaspora sp.": {}
              }
            },
            "Pigoraptor": {
              "Pigoraptor vietnamica": {},
              "Pigoraptor chileana": {}
            },
            "unclassified Filasterea": {
              "Filasterea sp.": {}
            },
            "Txikisporidae": {
              "Txikispora": {
                "Txikispora philomaios": {}
              }
            }
          }
        }
      }
    }
  }
}